ming/__init__.py
ming/base.py
ming/base.pyi
ming/compat.py
ming/config.py
ming/datastore.py
ming/declarative.py
ming/declarative.pyi
ming/encryption.py
ming/exc.py
ming/fs.py
ming/metadata.py
ming/metadata.pyi
ming/mim.py
ming/py.typed
ming/schema.py
ming/session.py
ming/utils.py
ming/validators.py
ming/version.py
ming/odm/__init__.py
ming/odm/base.py
ming/odm/declarative.py
ming/odm/declarative.pyi
ming/odm/icollection.py
ming/odm/identity_map.py
ming/odm/mapper.py
ming/odm/mapper.pyi
ming/odm/middleware.py
ming/odm/odmsession.py
ming/odm/property.py
ming/odm/property.pyi
ming/odm/unit_of_work.py
ming/orm/__init__.py
ming/orm/base.py
ming/orm/declarative.py
ming/orm/middleware.py
ming/orm/ormsession.py
ming/orm/property.py
ming/tests/__init__.py
ming/tests/test_base.py
ming/tests/test_datastore.py
ming/tests/test_declarative.py
ming/tests/test_encryption.py
ming/tests/test_functional.py
ming/tests/test_gridfs.py
ming/tests/test_middleware.py
ming/tests/test_mim.py
ming/tests/test_schema.py
ming/tests/test_session.py
ming/tests/test_utils.py
ming/tests/odm/__init__.py
ming/tests/odm/test_declarative.py
ming/tests/odm/test_instrumented_collections.py
ming/tests/odm/test_mapper.py
ming-0.16.0.dist-info/licenses/LICENSE.txt
ming-0.16.0.dist-info/METADATA
ming-0.16.0.dist-info/WHEEL
ming-0.16.0.dist-info/entry_points.txt
ming-0.16.0.dist-info/top_level.txt
ming-0.16.0.dist-info/zip-safe
ming-0.16.0.dist-info/RECORD
